[
    {
        "Subject":  "GATO File Log Report",
        "ExpectedTime":  "2:41 AM",
        "ReceivedTime":  "5/25/2026 2:40 AM",
        "Status":  "Present",
        "SortTime":  160.48333333333335
    },
    {
        "Subject":  "MAXIT Upload Report",
        "ExpectedTime":  "2:47 AM",
        "ReceivedTime":  "5/25/2026 2:47 AM",
        "Status":  "Present",
        "SortTime":  167.20000000000002
    },
    {
        "Subject":  "Daily SOD to ITG Bahamas Inc",
        "ExpectedTime":  "3:06 AM",
        "ReceivedTime":  "5/25/2026 3:00 AM",
        "Status":  "Present",
        "SortTime":  180.36666666666667
    },
    {
        "Subject":  "Daily ETB to GTN Middle East",
        "ExpectedTime":  "3:04 AM",
        "ReceivedTime":  "5/25/2026 3:00 AM",
        "Status":  "Present",
        "SortTime":  180.41666666666666
    },
    {
        "Subject":  "Daily SOD to Hexstone Capital LLC",
        "ExpectedTime":  "3:06 AM",
        "ReceivedTime":  "5/25/2026 3:00 AM",
        "Status":  "Present",
        "SortTime":  180.41666666666666
    },
    {
        "Subject":  "Daily SOD Files for Bull Markets",
        "ExpectedTime":  "3:06 AM",
        "ReceivedTime":  "5/25/2026 3:00 AM",
        "Status":  "Present",
        "SortTime":  180.48333333333335
    },
    {
        "Subject":  "DAILY CASH ACCT SD REPORT",
        "ExpectedTime":  "3:46 AM",
        "ReceivedTime":  "5/25/2026 3:45 AM",
        "Status":  "Present",
        "SortTime":  225.91666666666666
    },
    {
        "Subject":  "Daily SOD Files MMCD",
        "ExpectedTime":  "3:05 AM",
        "ReceivedTime":  "",
        "Status":  "Missing",
        "SortTime":  999999
    },
    {
        "Subject":  "Daily VCPS Position to Ambrus",
        "ExpectedTime":  "3:06 AM",
        "ReceivedTime":  "",
        "Status":  "Missing",
        "SortTime":  999999
    },
    {
        "Subject":  "Daily SOD Files to ASB Bank Corp",
        "ExpectedTime":  "3:18 AM",
        "ReceivedTime":  "",
        "Status":  "Missing",
        "SortTime":  999999
    },
    {
        "Subject":  "Daily Position File",
        "ExpectedTime":  "3:19 AM",
        "ReceivedTime":  "",
        "Status":  "Missing",
        "SortTime":  999999
    },
    {
        "Subject":  "Daily SOD Files to Andes Investments Group",
        "ExpectedTime":  "3:18 AM",
        "ReceivedTime":  "",
        "Status":  "Missing",
        "SortTime":  999999
    }
]
